datasette_debug_permissions.py
datasette_debug_permissions-0.1.dist-info/LICENSE
datasette_debug_permissions-0.1.dist-info/METADATA
datasette_debug_permissions-0.1.dist-info/WHEEL
datasette_debug_permissions-0.1.dist-info/entry_points.txt
datasette_debug_permissions-0.1.dist-info/top_level.txt
datasette_debug_permissions-0.1.dist-info/RECORD
