Metadata-Version: 2.1
Name: datasette-debug-permissions
Version: 0.1
Summary: A Datasette plugin that outputs debug information about permission checks
Author: Simon Willison
License: Apache-2.0
Project-URL: Homepage, https://github.com/datasette/datasette-debug-permissions
Project-URL: Changelog, https://github.com/datasette/datasette-debug-permissions/releases
Project-URL: Issues, https://github.com/datasette/datasette-debug-permissions/issues
Project-URL: CI, https://github.com/datasette/datasette-debug-permissions/actions
Classifier: License :: OSI Approved :: Apache Software License
Classifier: Framework :: Datasette
License-File: LICENSE
Requires-Dist: datasette
Provides-Extra: test
Requires-Dist: pytest ; extra == 'test'
